src/test_proj/__about__.py
src/test_proj/__init__.py
src/test_proj/app.py
madskris_test_proj-0.19.0.dist-info/METADATA
madskris_test_proj-0.19.0.dist-info/WHEEL
madskris_test_proj-0.19.0.dist-info/licenses/LICENSE.txt
madskris_test_proj-0.19.0.dist-info/RECORD
