Metadata-Version: 2.3
Name: MadsKris.test-proj
Version: 0.19.0
Project-URL: Documentation, https://github.com/U.N. Owen/test-proj#readme
Project-URL: Issues, https://github.com/U.N. Owen/test-proj/issues
Project-URL: Source, https://github.com/U.N. Owen/test-proj
Author-email: "U.N. Owen" <void@some.where>
License-Expression: MIT
License-File: LICENSE.txt
Classifier: Development Status :: 4 - Beta
Classifier: Programming Language :: Python
Classifier: Programming Language :: Python :: 3.8
Classifier: Programming Language :: Python :: 3.9
Classifier: Programming Language :: Python :: 3.10
Classifier: Programming Language :: Python :: 3.11
Classifier: Programming Language :: Python :: 3.12
Classifier: Programming Language :: Python :: Implementation :: CPython
Classifier: Programming Language :: Python :: Implementation :: PyPy
Requires-Python: >=3.8
